{"success":true,"duration":30.022,"key":"B","segments":[{"start":0.0,"end":1.834,"chord":"E"},{"start":1.834,"end":1.858,"chord":"Eadd9"},{"start":1.858,"end":1.904,"chord":"F#7/E"},{"start":1.904,"end":2.74,"chord":"F#/E"},{"start":2.74,"end":2.972,"chord":"F#"},{"start":2.972,"end":3.808,"chord":"F#/E"},{"start":3.808,"end":4.087,"chord":"F#"},{"start":4.087,"end":4.458,"chord":"F#/E"},{"start":4.458,"end":4.574,"chord":"F#"},{"start":4.574,"end":4.598,"chord":"F#/Eb"},{"start":4.598,"end":6.664,"chord":"Ebm7"},{"start":6.664,"end":6.78,"chord":"F#/Eb"},{"start":6.78,"end":6.827,"chord":"Bmaj7"},{"start":6.827,"end":7.105,"chord":"Ebm7"},{"start":7.105,"end":7.152,"chord":"Eb"},{"start":7.152,"end":7.175,"chord":"B/Eb"},{"start":7.175,"end":8.406,"chord":"Abm7"},{"start":8.406,"end":8.452,"chord":"Abm"},{"start":8.452,"end":8.475,"chord":"Emaj7/Ab"},{"start":8.475,"end":8.8,"chord":"E/Ab"},{"start":8.8,"end":8.87,"chord":"Abm7"},{"start":8.87,"end":9.009,"chord":"Abm7/F#"},{"start":9.009,"end":9.729,"chord":"Abm7"},{"start":9.729,"end":9.822,"chord":"Abm"},{"start":9.822,"end":10.728,"chord":"C#m7"},{"start":10.728,"end":11.842,"chord":"E/C#"},{"start":11.842,"end":11.958,"chord":"C#m7"},{"start":11.958,"end":12.074,"chord":"E/C#"},{"start":12.074,"end":12.283,"chord":"C#m7"},{"start":12.283,"end":12.307,"chord":"C#"},{"start":12.307,"end":12.33,"chord":"F#5/C#"},{"start":12.33,"end":12.353,"chord":"F#5"},{"start":12.353,"end":13.351,"chord":"F#"},{"start":13.351,"end":13.375,"chord":"F#sus4"},{"start":13.375,"end":13.468,"chord":"B/F#"},{"start":13.468,"end":13.491,"chord":"B5/F#"},{"start":13.491,"end":13.56,"chord":"Bsus2/F#"},{"start":13.56,"end":13.886,"chord":"F#sus4"},{"start":13.886,"end":13.909,"chord":"F#5"},{"start":13.909,"end":14.28,"chord":"F#sus4"},{"start":14.28,"end":14.443,"chord":"F#"},{"start":14.443,"end":14.489,"chord":"F#sus4"},{"start":14.489,"end":14.605,"chord":"F#5"},{"start":14.605,"end":14.698,"chord":"F#"},{"start":14.698,"end":15.0,"chord":"F#5"},{"start":15.0,"end":15.023,"chord":"F#sus4"},{"start":15.023,"end":15.047,"chord":"B5/F#"},{"start":15.047,"end":16.44,"chord":"B"},{"start":16.44,"end":17.345,"chord":"B5"},{"start":17.345,"end":17.717,"chord":"B"},{"start":17.717,"end":18.553,"chord":"B/F#"},{"start":18.553,"end":18.576,"chord":"B5/F#"},{"start":18.576,"end":18.599,"chord":"F#"},{"start":18.599,"end":18.855,"chord":"B5/F#"},{"start":18.855,"end":18.878,"chord":"B5"},{"start":18.878,"end":19.296,"chord":"B"},{"start":19.296,"end":19.598,"chord":"B7"},{"start":19.598,"end":20.255,"chord":"B"},{"start":20.255,"end":20.279,"chord":"Esus2"},{"start":20.279,"end":20.534,"chord":"E"},{"start":20.534,"end":20.975,"chord":"Emaj7"},{"start":20.975,"end":21.231,"chord":"E"},{"start":21.231,"end":21.277,"chord":"Emaj7"},{"start":21.277,"end":22.159,"chord":"E"},{"start":22.159,"end":22.345,"chord":"E5"},{"start":22.345,"end":22.392,"chord":"E"},{"start":22.624,"end":22.879,"chord":"E"},{"start":22.879,"end":22.926,"chord":"F#/E"},{"start":22.926,"end":23.111,"chord":"F#7/E"},{"start":23.111,"end":23.135,"chord":"E"},{"start":23.135,"end":23.297,"chord":"F#7/E"},{"start":23.297,"end":23.32,"chord":"F#5/E"},{"start":23.32,"end":23.878,"chord":"F#7/E"},{"start":23.878,"end":23.901,"chord":"F#5/E"},{"start":23.901,"end":24.435,"chord":"F#7/E"},{"start":24.435,"end":24.505,"chord":"F#/E"},{"start":24.505,"end":24.551,"chord":"B5"},{"start":24.551,"end":25.039,"chord":"Bmaj7"},{"start":25.039,"end":25.178,"chord":"B5"},{"start":25.178,"end":25.224,"chord":"Bsus2"},{"start":25.224,"end":25.526,"chord":"F#/B"},{"start":25.526,"end":25.55,"chord":"F#/Eb"},{"start":25.55,"end":26.78,"chord":"Ebm"},{"start":26.78,"end":27.105,"chord":"Ebm7"},{"start":27.105,"end":27.616,"chord":"Ebm"},{"start":27.616,"end":27.639,"chord":"B5/Eb"},{"start":27.639,"end":27.872,"chord":"B5"},{"start":27.895,"end":28.127,"chord":"Eb"},{"start":28.127,"end":28.173,"chord":"Ab5"},{"start":28.173,"end":28.963,"chord":"Abm"},{"start":28.963,"end":29.079,"chord":"Abm7"},{"start":29.079,"end":29.218,"chord":"Abm"},{"start":29.218,"end":29.381,"chord":"Ab"}],"displaySegments":[{"start":0.0,"end":1.904,"chord":"E"},{"start":1.904,"end":4.574,"chord":"F#"},{"start":4.574,"end":7.175,"chord":"Ebm"},{"start":7.175,"end":9.729,"chord":"Abm"},{"start":9.729,"end":10.728,"chord":"C#m"},{"start":10.728,"end":12.353,"chord":"E"},{"start":12.353,"end":15.047,"chord":"F#"},{"start":15.047,"end":21.277,"chord":"B"},{"start":21.277,"end":23.32,"chord":"E"},{"start":23.32,"end":25.55,"chord":"F#7"},{"start":25.55,"end":28.173,"chord":"Ebm"},{"start":28.173,"end":29.381,"chord":"Abm"}],"simplifiedDisplaySegments":[{"start":0.0,"end":1.904,"chord":"E"},{"start":1.904,"end":4.574,"chord":"F#"},{"start":4.574,"end":7.175,"chord":"Ebm"},{"start":7.175,"end":9.729,"chord":"Abm"},{"start":9.729,"end":10.728,"chord":"C#m"},{"start":10.728,"end":12.353,"chord":"E"},{"start":12.353,"end":15.047,"chord":"F#"},{"start":15.047,"end":21.277,"chord":"B"},{"start":21.277,"end":23.32,"chord":"E"},{"start":23.32,"end":25.55,"chord":"F#7"},{"start":25.55,"end":28.173,"chord":"Ebm"},{"start":28.173,"end":29.381,"chord":"Abm"}],"chordChartSegments":[{"start":0.0,"end":1.904,"chord":"E","confidence":1.0},{"start":1.904,"end":4.574,"chord":"F#","confidence":1.0},{"start":4.574,"end":7.175,"chord":"Ebm","confidence":1.0},{"start":7.175,"end":9.729,"chord":"Abm","confidence":1.0},{"start":9.729,"end":10.728,"chord":"C#m","confidence":1.0},{"start":10.728,"end":12.353,"chord":"E","confidence":1.0},{"start":12.353,"end":15.047,"chord":"F#","confidence":1.0},{"start":15.047,"end":21.277,"chord":"B","confidence":1.0},{"start":21.277,"end":23.32,"chord":"E","confidence":1.0},{"start":23.32,"end":25.55,"chord":"F#","confidence":1.0},{"start":25.55,"end":28.173,"chord":"Ebm","confidence":1.0},{"start":28.173,"end":29.381,"chord":"Abm","confidence":1.0}],"timingVariants":{"normal":{"displaySegments":[{"start":0.0,"end":1.904,"chord":"E"},{"start":1.904,"end":4.574,"chord":"F#"},{"start":4.574,"end":7.175,"chord":"Ebm"},{"start":7.175,"end":9.729,"chord":"Abm"},{"start":9.729,"end":10.728,"chord":"C#m"},{"start":10.728,"end":12.353,"chord":"E"},{"start":12.353,"end":15.047,"chord":"F#"},{"start":15.047,"end":21.277,"chord":"B"},{"start":21.277,"end":23.32,"chord":"E"},{"start":23.32,"end":25.55,"chord":"F#7"},{"start":25.55,"end":28.173,"chord":"Ebm"},{"start":28.173,"end":29.381,"chord":"Abm"}],"simplifiedDisplaySegments":[{"start":0.0,"end":1.904,"chord":"E"},{"start":1.904,"end":4.574,"chord":"F#"},{"start":4.574,"end":7.175,"chord":"Ebm"},{"start":7.175,"end":9.729,"chord":"Abm"},{"start":9.729,"end":10.728,"chord":"C#m"},{"start":10.728,"end":12.353,"chord":"E"},{"start":12.353,"end":15.047,"chord":"F#"},{"start":15.047,"end":21.277,"chord":"B"},{"start":21.277,"end":23.32,"chord":"E"},{"start":23.32,"end":25.55,"chord":"F#7"},{"start":25.55,"end":28.173,"chord":"Ebm"},{"start":28.173,"end":29.381,"chord":"Abm"}],"chordChartSegments":[{"start":0.0,"end":1.904,"chord":"E","confidence":1.0},{"start":1.904,"end":4.574,"chord":"F#","confidence":1.0},{"start":4.574,"end":7.175,"chord":"Ebm","confidence":1.0},{"start":7.175,"end":9.729,"chord":"Abm","confidence":1.0},{"start":9.729,"end":10.728,"chord":"C#m","confidence":1.0},{"start":10.728,"end":12.353,"chord":"E","confidence":1.0},{"start":12.353,"end":15.047,"chord":"F#","confidence":1.0},{"start":15.047,"end":21.277,"chord":"B","confidence":1.0},{"start":21.277,"end":23.32,"chord":"E","confidence":1.0},{"start":23.32,"end":25.55,"chord":"F#","confidence":1.0},{"start":25.55,"end":28.173,"chord":"Ebm","confidence":1.0},{"start":28.173,"end":29.381,"chord":"Abm","confidence":1.0}]},"noAbsorb":{"displaySegments":[{"start":0.0,"end":1.834,"chord":"E"},{"start":1.904,"end":2.74,"chord":"F#"},{"start":2.972,"end":4.087,"chord":"F#"},{"start":4.598,"end":7.105,"chord":"Ebm"},{"start":7.175,"end":8.406,"chord":"Abm"},{"start":8.475,"end":8.8,"chord":"E"},{"start":9.822,"end":10.728,"chord":"C#m"},{"start":10.728,"end":11.842,"chord":"E"},{"start":11.842,"end":11.958,"chord":"C#m"},{"start":12.353,"end":13.351,"chord":"F#"},{"start":13.909,"end":14.28,"chord":"F#"},{"start":14.698,"end":15.0,"chord":"F#"},{"start":15.047,"end":17.345,"chord":"B"},{"start":17.717,"end":18.553,"chord":"B"},{"start":18.878,"end":19.296,"chord":"B"},{"start":19.598,"end":20.255,"chord":"B"},{"start":20.534,"end":20.975,"chord":"E"},{"start":21.277,"end":22.159,"chord":"E"},{"start":22.624,"end":22.879,"chord":"E"},{"start":23.32,"end":23.878,"chord":"F#7"},{"start":24.551,"end":25.039,"chord":"B"},{"start":25.55,"end":27.616,"chord":"Ebm"},{"start":28.173,"end":28.963,"chord":"Abm"},{"start":29.218,"end":29.381,"chord":"Ab"}],"simplifiedDisplaySegments":[{"start":0.0,"end":1.834,"chord":"E"},{"start":1.904,"end":2.74,"chord":"F#"},{"start":2.972,"end":4.087,"chord":"F#"},{"start":4.598,"end":7.105,"chord":"Ebm"},{"start":7.175,"end":8.406,"chord":"Abm"},{"start":8.475,"end":8.8,"chord":"E"},{"start":9.822,"end":10.728,"chord":"C#m"},{"start":10.728,"end":11.842,"chord":"E"},{"start":11.842,"end":11.958,"chord":"C#m"},{"start":12.353,"end":13.351,"chord":"F#"},{"start":13.909,"end":14.28,"chord":"F#"},{"start":14.698,"end":15.0,"chord":"F#"},{"start":15.047,"end":17.345,"chord":"B"},{"start":17.717,"end":18.553,"chord":"B"},{"start":18.878,"end":19.296,"chord":"B"},{"start":19.598,"end":20.255,"chord":"B"},{"start":20.534,"end":20.975,"chord":"E"},{"start":21.277,"end":22.159,"chord":"E"},{"start":22.624,"end":22.879,"chord":"E"},{"start":23.32,"end":23.878,"chord":"F#7"},{"start":24.551,"end":25.039,"chord":"B"},{"start":25.55,"end":27.616,"chord":"Ebm"},{"start":28.173,"end":28.963,"chord":"Abm"},{"start":29.218,"end":29.381,"chord":"Ab"}],"chordChartSegments":[{"start":0.0,"end":1.834,"chord":"E","confidence":1.0},{"start":1.904,"end":2.74,"chord":"F#","confidence":1.0},{"start":2.972,"end":4.087,"chord":"F#","confidence":1.0},{"start":4.598,"end":7.105,"chord":"Ebm","confidence":1.0},{"start":7.175,"end":8.406,"chord":"Abm","confidence":1.0},{"start":8.475,"end":8.8,"chord":"E","confidence":1.0},{"start":9.822,"end":10.728,"chord":"C#m","confidence":1.0},{"start":10.728,"end":11.842,"chord":"E","confidence":1.0},{"start":11.842,"end":11.958,"chord":"C#m","confidence":1.0},{"start":12.353,"end":13.351,"chord":"F#","confidence":1.0},{"start":13.909,"end":14.28,"chord":"F#","confidence":1.0},{"start":14.698,"end":15.0,"chord":"F#","confidence":1.0},{"start":15.047,"end":17.345,"chord":"B","confidence":1.0},{"start":17.717,"end":18.553,"chord":"B","confidence":1.0},{"start":18.878,"end":19.296,"chord":"B","confidence":1.0},{"start":19.598,"end":20.255,"chord":"B","confidence":1.0},{"start":20.534,"end":20.975,"chord":"E","confidence":1.0},{"start":21.277,"end":22.159,"chord":"E","confidence":1.0},{"start":22.624,"end":22.879,"chord":"E","confidence":1.0},{"start":23.32,"end":23.878,"chord":"F#","confidence":1.0},{"start":24.551,"end":25.039,"chord":"B","confidence":1.0},{"start":25.55,"end":27.616,"chord":"Ebm","confidence":1.0},{"start":28.173,"end":28.963,"chord":"Abm","confidence":1.0},{"start":29.218,"end":29.381,"chord":"Ab","confidence":1.0}]},"timing":{"displaySegments":[{"start":0.0,"end":1.834,"chord":"E"},{"start":1.904,"end":4.417,"chord":"F#"},{"start":4.417,"end":7.105,"chord":"Ebm"},{"start":7.175,"end":8.406,"chord":"Abm"},{"start":8.475,"end":11.732,"chord":"E"},{"start":11.732,"end":15.0,"chord":"F#"},{"start":15.047,"end":20.255,"chord":"B"},{"start":20.534,"end":24.148,"chord":"E"},{"start":24.148,"end":27.616,"chord":"Ebm"},{"start":28.173,"end":29.381,"chord":"Abm"}],"simplifiedDisplaySegments":[{"start":0.0,"end":1.834,"chord":"E"},{"start":1.904,"end":4.417,"chord":"F#"},{"start":4.417,"end":7.105,"chord":"Ebm"},{"start":7.175,"end":8.406,"chord":"Abm"},{"start":8.475,"end":11.732,"chord":"E"},{"start":11.732,"end":15.0,"chord":"F#"},{"start":15.047,"end":20.255,"chord":"B"},{"start":20.534,"end":24.148,"chord":"E"},{"start":24.148,"end":27.616,"chord":"Ebm"},{"start":28.173,"end":29.381,"chord":"Abm"}],"chordChartSegments":[{"start":0.0,"end":1.834,"chord":"E","confidence":1.0},{"start":1.904,"end":4.417,"chord":"F#","confidence":1.0},{"start":4.417,"end":7.105,"chord":"Ebm","confidence":1.0},{"start":7.175,"end":8.406,"chord":"Abm","confidence":1.0},{"start":8.475,"end":11.732,"chord":"E","confidence":1.0},{"start":11.732,"end":15.0,"chord":"F#","confidence":1.0},{"start":15.047,"end":20.255,"chord":"B","confidence":1.0},{"start":20.534,"end":24.148,"chord":"E","confidence":1.0},{"start":24.148,"end":27.616,"chord":"Ebm","confidence":1.0},{"start":28.173,"end":29.381,"chord":"Abm","confidence":1.0}]},"timingCompact":{"displaySegments":[{"start":0.0,"end":1.834,"chord":"E"},{"start":1.904,"end":4.417,"chord":"F#"},{"start":4.417,"end":7.105,"chord":"Ebm"},{"start":7.175,"end":8.406,"chord":"Abm"},{"start":8.475,"end":11.732,"chord":"E"},{"start":11.732,"end":15.0,"chord":"F#"},{"start":15.047,"end":20.255,"chord":"B"},{"start":20.534,"end":24.148,"chord":"E"},{"start":24.148,"end":27.616,"chord":"Ebm"},{"start":28.173,"end":29.381,"chord":"Abm"}],"simplifiedDisplaySegments":[{"start":0.0,"end":1.834,"chord":"E"},{"start":1.904,"end":4.417,"chord":"F#"},{"start":4.417,"end":7.105,"chord":"Ebm"},{"start":7.175,"end":8.406,"chord":"Abm"},{"start":8.475,"end":11.732,"chord":"E"},{"start":11.732,"end":15.0,"chord":"F#"},{"start":15.047,"end":20.255,"chord":"B"},{"start":20.534,"end":24.148,"chord":"E"},{"start":24.148,"end":27.616,"chord":"Ebm"},{"start":28.173,"end":29.381,"chord":"Abm"}],"chordChartSegments":[{"start":0.0,"end":1.834,"chord":"E","confidence":1.0},{"start":1.904,"end":4.417,"chord":"F#","confidence":1.0},{"start":4.417,"end":7.105,"chord":"Ebm","confidence":1.0},{"start":7.175,"end":8.406,"chord":"Abm","confidence":1.0},{"start":8.475,"end":11.732,"chord":"E","confidence":1.0},{"start":11.732,"end":15.0,"chord":"F#","confidence":1.0},{"start":15.047,"end":20.255,"chord":"B","confidence":1.0},{"start":20.534,"end":24.148,"chord":"E","confidence":1.0},{"start":24.148,"end":27.616,"chord":"Ebm","confidence":1.0},{"start":28.173,"end":29.381,"chord":"Abm","confidence":1.0}]},"playableCompact":{"displaySegments":[{"start":0.0,"end":1.834,"chord":"E"},{"start":1.904,"end":4.417,"chord":"F#"},{"start":4.417,"end":7.105,"chord":"Ebm"},{"start":7.175,"end":8.406,"chord":"Abm"},{"start":8.475,"end":11.732,"chord":"E"},{"start":11.732,"end":15.0,"chord":"F#"},{"start":15.047,"end":20.255,"chord":"B"},{"start":20.534,"end":24.148,"chord":"E"},{"start":24.148,"end":27.616,"chord":"Ebm"},{"start":28.173,"end":29.381,"chord":"Abm"}],"simplifiedDisplaySegments":[{"start":0.0,"end":1.834,"chord":"E"},{"start":1.904,"end":4.417,"chord":"F#"},{"start":4.417,"end":7.105,"chord":"Ebm"},{"start":7.175,"end":8.406,"chord":"Abm"},{"start":8.475,"end":11.732,"chord":"E"},{"start":11.732,"end":15.0,"chord":"F#"},{"start":15.047,"end":20.255,"chord":"B"},{"start":20.534,"end":24.148,"chord":"E"},{"start":24.148,"end":27.616,"chord":"Ebm"},{"start":28.173,"end":29.381,"chord":"Abm"}],"chordChartSegments":[{"start":0.0,"end":1.834,"chord":"E","confidence":1.0},{"start":1.904,"end":4.417,"chord":"F#","confidence":1.0},{"start":4.417,"end":7.105,"chord":"Ebm","confidence":1.0},{"start":7.175,"end":8.406,"chord":"Abm","confidence":1.0},{"start":8.475,"end":11.732,"chord":"E","confidence":1.0},{"start":11.732,"end":15.0,"chord":"F#","confidence":1.0},{"start":15.047,"end":20.255,"chord":"B","confidence":1.0},{"start":20.534,"end":24.148,"chord":"E","confidence":1.0},{"start":24.148,"end":27.616,"chord":"Ebm","confidence":1.0},{"start":28.173,"end":29.381,"chord":"Abm","confidence":1.0}]}},"timingVariantStats":{"normal":{"displayCount":12,"simplifiedCount":12,"chordChartCount":12},"noAbsorb":{"displayCount":24,"simplifiedCount":24,"chordChartCount":24},"timing":{"displayCount":10,"simplifiedCount":10,"chordChartCount":10,"absorbedCount":13,"keptShortCount":3,"snappedBoundaryCount":4},"timingCompact":{"displayCount":10,"simplifiedCount":10,"chordChartCount":10,"compressedCount":0,"preservedTransitionCount":0},"playableCompact":{"displayCount":10,"simplifiedCount":10,"chordChartCount":10,"compressedCount":0,"simplifiedChordNameCount":0,"preservedTransitionCount":0,"targetDensityAppliedCount":0}},"debug":{"duration":30.022,"chunkDuration":20.0,"chunkCount":2,"chunks":[{"chunk_index":0,"start":0.0,"end":20.0,"segment_count":58},{"chunk_index":1,"start":20.0,"end":30.022,"segment_count":36}],"input_feature_shape":[1,1,144,862],"model_input_shape":[1,1,144,862],"output_shapes":{"root_logits":[1,862,13],"bass_logits":[1,862,13],"chord_logits":[1,862,12]},"decode_mode":"simple_root_bass_chroma","raw_preview":{},"keyScores":[{"key":"B","score":89.768,"supports":[{"chord":"E","contrib":11.37},{"chord":"B","contrib":10.224},{"chord":"F#/E","contrib":7.776},{"chord":"F#","contrib":6.854},{"chord":"F#7/E","contrib":6.237}]},{"key":"E","score":70.789,"supports":[{"chord":"E","contrib":12.791},{"chord":"B","contrib":10.224},{"chord":"B5","contrib":4.846},{"chord":"E/C#","contrib":4.428},{"chord":"Abm7","contrib":3.74}]},{"key":"Abm","score":67.61,"supports":[{"chord":"Abm7","contrib":7.586},{"chord":"E","contrib":6.928},{"chord":"Ebm7","contrib":6.406},{"chord":"B","contrib":5.822},{"chord":"F#/E","contrib":5.076}]},{"key":"F#","score":63.184,"supports":[{"chord":"B","contrib":9.088},{"chord":"F#/E","contrib":7.776},{"chord":"Ebm7","contrib":7.607},{"chord":"F#","contrib":6.854},{"chord":"Ebm","contrib":4.962}]},{"key":"C#m","score":59.555,"supports":[{"chord":"E","contrib":7.284},{"chord":"B","contrib":6.674},{"chord":"Abm7","contrib":5.129},{"chord":"F#/E","contrib":4.428},{"chord":"C#m7","contrib":4.37}]}],"keyConfidence":0.211,"rawSegmentCount":93,"displaySegmentCount":12,"removedShortSegmentCount":74,"sameSecondConflictCount":0,"displayChordText":["00:00 | E | F# | Ebm | Abm |","00:09 | C#m | E | F# | B |","00:21 | E | F#7 | Ebm | Abm |"],"simplifiedChordText":["00:00 | E | F# | Ebm | Abm |","00:09 | C#m | E | F# | B |","00:21 | E | F#7 | Ebm | Abm |"],"simplifiedSegmentCount":12,"chordChartSegmentCount":12,"absorbedShortChordCount":0,"absorbedOutOfKeyCount":0,"absorbedComplexChordCount":0,"absorbedLowConfidenceCount":0,"simplifiedComplexChordCount":1,"estimatedKey":"B","chordChartText":"E F# Ebm Abm\nC#m E F# B\nE F# Ebm Abm","chordChartSourceSegmentCount":12,"timingShortSegments":[{"chord":"E","start":8.475,"end":8.8,"duration":0.325,"onsetScore":0.6354,"chromaChangeScore":0.123,"confidenceScore":1.0,"beatProximityScore":0.6807,"musicTheoryBonus":0.04,"noisePenalty":0.0,"keepScore":0.6014,"decision":"keep"},{"chord":"E","start":8.475,"end":8.8,"duration":0.325,"onsetScore":0.6354,"chromaChangeScore":0.123,"confidenceScore":1.0,"beatProximityScore":0.6807,"musicTheoryBonus":0.0,"noisePenalty":0.0,"keepScore":0.5614,"decision":"keep"},{"chord":"E","start":8.475,"end":8.8,"duration":0.325,"onsetScore":0.6354,"chromaChangeScore":0.123,"confidenceScore":1.0,"beatProximityScore":0.6807,"musicTheoryBonus":0.0,"noisePenalty":0.0,"keepScore":0.5614,"decision":"keep"},{"chord":"F#","start":1.904,"end":2.74,"duration":0.836,"onsetScore":0.4613,"chromaChangeScore":0.0937,"confidenceScore":1.0,"beatProximityScore":0.9997,"musicTheoryBonus":0.0,"noisePenalty":0.0,"keepScore":0.5395,"decision":"absorb","absorbInto":"next","absorbReason":"same_chord_next"},{"chord":"C#m","start":9.822,"end":10.728,"duration":0.906,"onsetScore":0.6334,"chromaChangeScore":0.1408,"confidenceScore":1.0,"beatProximityScore":0.5598,"musicTheoryBonus":0.0,"noisePenalty":0.0,"keepScore":0.5479,"decision":"absorb","absorbInto":"next","absorbReason":"higher_evidence_neighbor"},{"chord":"C#m","start":11.842,"end":11.958,"duration":0.116,"onsetScore":0.6008,"chromaChangeScore":0.0966,"confidenceScore":1.0,"beatProximityScore":0.3806,"musicTheoryBonus":0.04,"noisePenalty":0.0,"keepScore":0.5363,"decision":"absorb","absorbInto":"next","absorbReason":"higher_evidence_neighbor"},{"chord":"F#","start":13.909,"end":14.28,"duration":0.371,"onsetScore":0.4647,"chromaChangeScore":0.0597,"confidenceScore":1.0,"beatProximityScore":0.1441,"musicTheoryBonus":0.0,"noisePenalty":0.08,"keepScore":0.3222,"decision":"absorb","absorbInto":"previous","absorbReason":"same_chord_prev"},{"chord":"F#","start":14.698,"end":15.0,"duration":0.302,"onsetScore":0.605,"chromaChangeScore":0.0808,"confidenceScore":1.0,"beatProximityScore":0.0807,"musicTheoryBonus":0.0,"noisePenalty":0.0,"keepScore":0.4481,"decision":"absorb","absorbInto":"previous","absorbReason":"same_chord_prev"},{"chord":"B","start":17.717,"end":18.553,"duration":0.836,"onsetScore":0.4253,"chromaChangeScore":0.1953,"confidenceScore":1.0,"beatProximityScore":0.4605,"musicTheoryBonus":0.0,"noisePenalty":0.0,"keepScore":0.4765,"decision":"absorb","absorbInto":"previous","absorbReason":"same_chord_prev"},{"chord":"B","start":18.878,"end":19.296,"duration":0.418,"onsetScore":0.4332,"chromaChangeScore":0.2303,"confidenceScore":1.0,"beatProximityScore":0.5604,"musicTheoryBonus":0.0,"noisePenalty":0.08,"keepScore":0.4248,"decision":"absorb","absorbInto":"previous","absorbReason":"same_chord_prev"},{"chord":"B","start":19.598,"end":20.255,"duration":0.657,"onsetScore":0.276,"chromaChangeScore":0.1159,"confidenceScore":1.0,"beatProximityScore":0.997,"musicTheoryBonus":0.0,"noisePenalty":0.0,"keepScore":0.4809,"decision":"absorb","absorbInto":"previous","absorbReason":"same_chord_prev"},{"chord":"E","start":20.534,"end":20.975,"duration":0.441,"onsetScore":0.2084,"chromaChangeScore":0.0958,"confidenceScore":1.0,"beatProximityScore":0.0759,"musicTheoryBonus":0.0,"noisePenalty":0.0,"keepScore":0.313,"decision":"absorb","absorbInto":"next","absorbReason":"same_chord_next"},{"chord":"E","start":22.624,"end":22.879,"duration":0.255,"onsetScore":0.3345,"chromaChangeScore":0.1319,"confidenceScore":1.0,"beatProximityScore":0.1541,"musicTheoryBonus":0.0,"noisePenalty":0.0,"keepScore":0.3798,"decision":"absorb","absorbInto":"previous","absorbReason":"same_chord_prev"},{"chord":"F#7","start":23.32,"end":23.878,"duration":0.558,"onsetScore":0.5469,"chromaChangeScore":0.1464,"confidenceScore":1.0,"beatProximityScore":0.186,"musicTheoryBonus":0.04,"noisePenalty":0.0,"keepScore":0.5032,"decision":"absorb","absorbInto":"previous","absorbReason":"higher_evidence_neighbor"},{"chord":"B","start":24.551,"end":25.039,"duration":0.488,"onsetScore":0.6005,"chromaChangeScore":0.1824,"confidenceScore":1.0,"beatProximityScore":0.1866,"musicTheoryBonus":0.04,"noisePenalty":0.0,"keepScore":0.5329,"decision":"absorb","absorbInto":"next","absorbReason":"higher_evidence_neighbor"},{"chord":"Abm","start":28.173,"end":28.963,"duration":0.79,"onsetScore":0.4532,"chromaChangeScore":0.2208,"confidenceScore":1.0,"beatProximityScore":0.5271,"musicTheoryBonus":0.04,"noisePenalty":0.0,"keepScore":0.5439,"decision":"absorb","absorbInto":"next","absorbReason":"higher_evidence_neighbor"}],"timingBoundarySnaps":[{"old_t":4.087,"new_t":4.417,"delta":0.33,"reason":"onset_chroma_beat"},{"old_t":8.8,"new_t":9.05,"delta":0.25,"reason":"onset_chroma_beat"},{"old_t":11.842,"new_t":11.732,"delta":-0.11,"reason":"onset_chroma_beat"},{"old_t":23.878,"new_t":24.148,"delta":0.27,"reason":"onset_chroma_beat"}],"timingAbsorbedCount":13,"timingKeptShortCount":3,"timingSnappedBoundaryCount":4,"timingCompactSegments":[{"chord":"Abm","start":7.175,"end":8.406,"duration":1.231,"confidence":1.0,"removableScore":0.0,"shortnessScore":0.1793,"sameFunctionScore":0.0,"lowConfidenceScore":0.0,"sandwichNoiseScore":0.0,"ornamentalChordScore":0.0,"transitionImportanceScore":0.3438,"strongEventScore":0.3222,"decision":"preserve","compressInto":"","reason":"below_removable_threshold"},{"chord":"E","start":8.475,"end":11.732,"duration":3.257,"confidence":0.408,"removableScore":0.0,"shortnessScore":0.0,"sameFunctionScore":0.0,"lowConfidenceScore":0.592,"sandwichNoiseScore":0.0,"ornamentalChordScore":0.0,"transitionImportanceScore":0.2186,"strongEventScore":0.3792,"decision":"preserve","compressInto":"","reason":"below_removable_threshold"}],"playableCompactActions":[]},"timing":{"receive_sec":3.500236198306084e-05,"ingest_sec":0.00019103987142443657,"inference_sec":1.7297165840864182,"total_sec":1.729945246130228}}